pytest_parametrization_annotation/__init__.py
pytest_parametrization_annotation/annotation.py
pytest_parametrization_annotation/functionality.py
pytest_parametrization_annotation/plugin.py
pytest_parametrization_annotation/py.typed
pytest_parametrization_annotation-1.0.0.dist-info/LICENSE
pytest_parametrization_annotation-1.0.0.dist-info/METADATA
pytest_parametrization_annotation-1.0.0.dist-info/WHEEL
pytest_parametrization_annotation-1.0.0.dist-info/entry_points.txt
pytest_parametrization_annotation-1.0.0.dist-info/RECORD
