Metadata-Version: 2.1
Name: pytest-parametrization-annotation
Version: 1.0.0
Summary: A pytest library for parametrizing tests using type hints.
Author: Fabian Haenel
Author-email: contact@fabian-haenel.io
Requires-Python: >=3.10
Classifier: Development Status :: 5 - Production/Stable
Classifier: Framework :: Pytest
Classifier: Intended Audience :: Developers
Classifier: License :: OSI Approved :: BSD License
Classifier: Programming Language :: Python :: 3
Classifier: Programming Language :: Python :: 3.10
Classifier: Programming Language :: Python :: 3.11
Classifier: Programming Language :: Python :: 3.12
Classifier: Programming Language :: Python :: 3 :: Only
Classifier: Programming Language :: Python :: 3.13
Classifier: Topic :: Software Development :: Testing
Classifier: Topic :: Software Development :: Testing :: Unit
Classifier: Topic :: Utilities
Classifier: Typing :: Typed
Requires-Dist: pytest (>=7)
